Metadata-Version: 1.0
Name: lazy-git
Version: 0.2
Summary: A streamlined REST API for access to Git repositories
Home-page: UNKNOWN
Author: UNKNOWN
Author-email: UNKNOWN
License: UNKNOWN
Platform: UNKNOWN
